{
    "title": "The Rise of AI Companions: Transforming Human Connections",
    "description": "Explore how AI companions are changing the landscape of human relationships, their potential benefits and challenges, and what the future holds for these digital confidants.",
    "content": "<h2>Introduction</h2>\n<p>In recent years, artificial intelligence has transcended its initial role as a mere tool to assist humans, evolving into companions that understand, engage with, and even offer emotional support. AI companions are becoming increasingly integrated into our daily lives, from virtual assistants like Siri or Alexa to more sophisticated applications designed for companionship, such as Replika or AI-driven chatbots. This blog post delves into the rise of AI companions, examining their impact on human relationships, the potential benefits they bring, and the ethical challenges we must navigate as we embrace this technological evolution.</p>\n<h2>The Evolution of AI Companions</h2>\n<p>AI companions have come a long way since their inception. Initially, they were programmed to perform specific tasks, such as scheduling appointments or answering queries. However, with advancements in natural language processing, machine learning, and emotional AI, these companions can now engage in meaningful conversations, adapt to users' emotions, and provide personalized experiences.</p>\n<h2>Benefits of AI Companions</h2>\n<ul>\n    <li><strong>Emotional Support:</strong> AI companions can provide a sense of belonging and emotional support, especially for individuals who may feel lonely or isolated. They offer a non-judgmental space for users to express their thoughts and feelings.</li>\n    <li><strong>Accessibility:</strong> AI companions are available 24/7, making them an ideal source of support for those who need someone to talk to at odd hours or who may not have access to traditional mental health resources.</li>\n    <li><strong>Personalization:</strong> Through machine learning, AI companions can learn about users' preferences, interests, and emotional states, allowing for tailored interactions that resonate with individual needs.</li>\n    <li><strong>Reducing Stigma:</strong> Engaging with an AI can help users feel more comfortable discussing their mental health and emotional struggles, potentially leading them to seek further help.</li>\n</ul>\n<h2>Challenges and Ethical Considerations</h2>\n<p>Despite their potential benefits, AI companions also present several challenges and ethical considerations:</p>\n<ul>\n    <li><strong>Dependency:</strong> There is a risk that individuals may become overly reliant on AI companions for emotional support, potentially neglecting real-life relationships and interactions.</li>\n    <li><strong>Privacy Concerns:</strong> The data collected by AI companions for personalization raises questions about user privacy and data security. Users must be aware of how their information is being used and stored.</li>\n    <li><strong>Emotional Manipulation:</strong> As AI companions become more sophisticated, there is the potential for emotional manipulation, where users may be influenced by their interactions in unintended ways.</li>\n    <li><strong>Authenticity:</strong> The question of what constitutes a 'real' relationship arises. Can an AI truly understand human emotions, or will it always be a simulation?</li>\n</ul>\n<h2>The Future of AI Companions</h2>\n<p>As technology continues to advance, the future of AI companions looks promising. We may see the integration of AI companions into more aspects of our lives, such as healthcare, education, and even customer service. Moreover, advancements in emotional AI could lead to more authentic interactions, bridging the gap between humans and machines.</p>\n<p>However, it is essential to approach this evolution with caution. Developers, ethicists, and users must engage in ongoing discussions about the implications of AI companions, ensuring that they enhance human connections rather than replace them.</p>\n<h2>Conclusion</h2>\n<p>The rise of AI companions is a testament to the incredible advancements in artificial intelligence. While they offer significant benefits in terms of emotional support and accessibility, we must remain vigilant about the challenges they pose. By fostering a balanced relationship with AI companions, we can harness their potential while preserving the essence of human connection. As we look to the future, let us navigate this journey thoughtfully, ensuring that AI serves to enrich our relationships rather than diminish them.</p>",
    "date": "2023-10-08",
    "id": "1730220441979"
}